{
  "id": 9,
  "name": "Mash recirculation",
  "notes": [
    "To control the temperature of the mash, the wort is pumped through the coil in the HLT. The water in the HLT will heat up the wort.",
    "This heat exchange is what gives the HERMS its name: heat excange recirculating mash system. By heating the mash indirectly, the wort will never get hotter than the HLT temperature. This prevents overheating and scorching.",
    "The setpoint of the HLT is dynamic and controlled by BrewPi, based on the temperature error in the mash tun.",
    "Because all heat that is generated in the HLT will eventually even out between the HLT and mash tun, the best performance can be achieved with little water in the HLT, just enough to submerge the coil. With less thermal mass in the HLT, we can make bigger temperature swings in the HLT without overshooting in the mash tun. A bigger temperature difference leads to faster rise times."
  ],
  "settings": [
    {
      "id": "HLT-in",
      "settings": {
        "pos": "open"
      }
    },
    {
      "id": "MT-in",
      "settings": {
        "pos": "open"
      }
    },
    {
      "id": "Coil-out",
      "settings": {
        "pos": "open"
      }
    },
    {
      "id": "Coil-in",
      "settings": {
        "pos": "open"
      }
    },
    {
      "id": "BK-in",
      "settings": {
        "pos": "closed"
      }
    },
    {
      "id": "MT-out",
      "settings": {
        "pos": "open"
      }
    },
    {
      "id": "BK-out",
      "settings": {
        "pos": "closed"
      }
    },
    {
      "id": "MT-spray",
      "settings": {
        "pos": "closed"
      }
    },
    {
      "id": "Water",
      "settings": {
        "pos": "closed"
      }
    },
    {
      "id": "Route-1",
      "settings": {
        "pos": "open"
      }
    },
    {
      "id": "Route-2",
      "settings": {
        "pos": "closed"
      }
    },
    {
      "id": "CFC-out",
      "settings": {
        "pos": "closed"
      }
    },
    {
      "id": "CFC-in",
      "settings": {
        "pos": "closed"
      }
    },
    {
      "id": "Drain",
      "settings": {
        "pos": "closed"
      }
    },
    {
      "id": "Water-fill",
      "settings": {
        "pos": "closed"
      }
    },
    {
      "id": "Water-cfc",
      "settings": {
        "pos": "closed"
      }
    },
    {
      "id": "Out",
      "settings": {
        "pos": "closed"
      }
    },
    {
      "id": "BK-spray",
      "settings": {
        "pos": "closed"
      }
    },
    {
      "id": "hlt",
      "settings": {
        "volume": 45,
        "liquid": "hotwater"
      }
    },
    {
      "id": "bk",
      "settings": {
        "volume": 0
      }
    },
    {
      "id": "mt",
      "settings": {
        "grain": 25,
        "volume": 30,
        "liquid": "wort"
      }
    },
    {
      "id": "in1",
      "settings": {
        "liquid": "water"
      }
    },
    {
      "id": "heat_hlt",
      "settings": {
        "duty": 10
      }
    },
    {
      "id": "heat_bk",
      "settings": {
        "duty": 0
      }
    },
    {
      "id": "p1",
      "settings":{
        "power": true,
        "speed": 100
      }
    },
    {
      "id": "p2",
      "settings":{
        "power": true,
        "speed": 100
      }
    },
    {
      "id": "sphlt",
      "settings": {
        "val": 68.3,
        "set": 69.2
      }
    },
    {
      "id": "spmt",
      "settings": {
        "val": 66.6,
        "set": 66.7
      }
    },
    {
      "id": "spbk",
      "settings": {
        "val": 20
      }
    },
    {
      "id": "cfcouttemp",
      "settings": {
        "val": 20
      }
    }
  ]
}